animl/__init__.py
animl/__main__.py
animl/classification.py
animl/detection.py
animl/export.py
animl/file_management.py
animl/generator.py
animl/model_architecture.py
animl/pipeline.py
animl/split.py
animl/test.py
animl/train.py
animl/video_processing.py
animl/models/__init__.py
animl/models/common.py
animl/models/download.py
animl/models/yolo.py
animl/pose/__init__.py
animl/pose/viewpoint.py
animl/reid/__init__.py
animl/reid/distance.py
animl/reid/inference.py
animl/reid/miewid.py
animl/utils/__init__.py
animl/utils/general.py
animl/utils/visualization.py
animl-3.1.1.dist-info/licenses/LICENSE
animl-3.1.1.dist-info/METADATA
animl-3.1.1.dist-info/WHEEL
animl-3.1.1.dist-info/top_level.txt
animl-3.1.1.dist-info/RECORD
