Metadata-Version: 2.4
Name: animl
Version: 3.1.1
Summary: Tools for classifying camera trap images
Author-email: Kyra Swanson <tswanson@sdzwa.org>
Project-URL: Homepage, https://github.com/conservationtechlab/animl-py
Keywords: camera trap,ecology,conservation,zoo,SDZWA,conservationtechlab
Requires-Python: >=3.12
License-File: LICENSE
Requires-Dist: dill>=0.4.0
Requires-Dist: numpy>=2.0.2
Requires-Dist: onnxruntime-gpu>=1.23.2
Requires-Dist: pandas>=2.2.2
Requires-Dist: pillow>=11.0.0
Requires-Dist: opencv-python>=4.12.0.88
Requires-Dist: scikit-learn>=1.5.2
Requires-Dist: timm>=1.0.9
Requires-Dist: torch>=2.6.0
Requires-Dist: torchvision>=0.21.0
Requires-Dist: tqdm>=4.66.5
Requires-Dist: ultralytics>=8.3.95
Requires-Dist: wget>=3.2
Provides-Extra: mlops
Requires-Dist: comet-ml>=3.54.2; extra == "mlops"
Dynamic: license-file
